nl_ego_cities/__init__.py
nl_ego_cities/city_coords.py
nl_ego_cities/load_city_data.py
nl_ego_cities-0.1.20.dist-info/LICENSE
nl_ego_cities-0.1.20.dist-info/METADATA
nl_ego_cities-0.1.20.dist-info/WHEEL
nl_ego_cities-0.1.20.dist-info/top_level.txt
nl_ego_cities-0.1.20.dist-info/RECORD
