Metadata-Version: 2.1
Name: nl-ego-cities
Version: 0.1.20
Summary: Data for Netherland Cities Coordinates
Home-page: https://github.com/cheerzhang/NLGeoCities
Author: L.Z
Author-email: zhangle@gmail.com
Project-URL: Bug Tracker, https://github.com/cheerzhang/NLGeoCities/issues
Classifier: Programming Language :: Python :: 3
Classifier: License :: OSI Approved :: MIT License
Classifier: Operating System :: OS Independent
Requires-Python: >=3.11.2
License-File: LICENSE
Requires-Dist: pandas >=0.25.1
Requires-Dist: numpy >=1.21.5
Requires-Dist: cdifflib >=1.2.6
